dumpobj/__init__.py
dumpobj/_dumpobj.py
dumpobj/_helper.py
dumpobj/node.py
dumpobj/formatter/base_formatter.py
dumpobj/formatter/color_formatter.py
dumpobj/formatter/json_formatter.py
dumpobj/formatter/plain_formatter.py
dumpobj-0.1.2.dist-info/licenses/LICENSE
dumpobj-0.1.2.dist-info/METADATA
dumpobj-0.1.2.dist-info/WHEEL
dumpobj-0.1.2.dist-info/top_level.txt
dumpobj-0.1.2.dist-info/RECORD
