Metadata-Version: 2.4
Name: dumpobj
Version: 0.1.2
Author-email: Ruilx <RuilxAlxa@qq.com>
License: MIT
Project-URL: Homepage, https://github.com/Ruilx/dumpobj
Project-URL: Repository, https://github.com/Ruilx/dumpobj
Classifier: License :: OSI Approved :: MIT License
Classifier: Programming Language :: Python :: 3 :: Only
Classifier: Programming Language :: Python :: 3.10
Classifier: Intended Audience :: Developers
Requires-Python: >=3.10
License-File: LICENSE
Dynamic: license-file
